ERL/AudioModelModule.py
ERL/AudioProcessModule.py
ERL/BimodalModule.py
ERL/PredictionsModule.py
ERL/TextModelModule.py
ERL/TextProcessingModule.py
ERL/__init__.py
ERL/classes/text_classes.npy
ERL/data/es/corpus.txt
ERL/data/es/f_ans001aes.wav
ERL/data/es/f_ans002aes.wav
ERL/data/es/f_ans003aes.wav
ERL/data/es/f_ans004aes.wav
ERL/data/es/f_ans007aes.wav
ERL/data/es/f_ans009aes.wav
ERL/data/es/f_ans009bes.wav
ERL/data/es/f_ans010aes.wav
ERL/data/es/f_ans010bes.wav
ERL/data/es/f_ans012aes.wav
ERL/data/es/f_ans018aes.wav
ERL/data/es/f_ans019aes.wav
ERL/data/es/f_ans024aes.wav
ERL/data/es/f_ans030aes.wav
ERL/data/es/f_ans040aes.wav
ERL/data/es/f_ans041aes.wav
ERL/data/es/f_ans041bes.wav
ERL/data/es/f_ans042aes.wav
ERL/data/es/f_ans042bes.wav
ERL/data/es/f_ans043aes.wav
ERL/data/es/f_ans044aes.wav
ERL/data/es/f_ans044bes.wav
ERL/data/es/f_ans045aes.wav
ERL/data/es/f_ans049aes.wav
ERL/data/es/f_ans050aes.wav
ERL/data/es/f_ans901aes.wav
ERL/data/es/f_ans901bes.wav
ERL/data/es/f_ans901ces.wav
ERL/data/es/f_ans902aes.wav
ERL/data/es/f_ans902bes.wav
ERL/data/es/f_ans902ces.wav
ERL/data/es/f_ans902des.wav
ERL/data/es/f_ans905aes.wav
ERL/data/es/f_dis008aes.wav
ERL/data/es/f_dis009aes.wav
ERL/data/es/f_dis014aes.wav
ERL/data/es/f_dis014bes.wav
ERL/data/es/f_dis016aes.wav
ERL/data/es/f_dis017aes.wav
ERL/data/es/f_dis019aes.wav
ERL/data/es/f_dis019bes.wav
ERL/data/es/f_dis019ces.wav
ERL/data/es/f_dis020aes.wav
ERL/data/es/f_dis024aes.wav
ERL/data/es/f_dis024bes.wav
ERL/data/es/f_dis025aes.wav
ERL/data/es/f_dis027aes.wav
ERL/data/es/f_dis027bes.wav
ERL/data/es/f_dis028aes.wav
ERL/data/es/f_dis029aes.wav
ERL/data/es/f_dis036aes.wav
ERL/data/es/f_dis036bes.wav
ERL/data/es/f_dis037aes.wav
ERL/data/es/f_dis038aes.wav
ERL/data/es/f_dis042aes.wav
ERL/data/es/f_dis043aes.wav
ERL/data/es/f_dis049aes.wav
ERL/data/es/f_dis108aes.wav
ERL/data/es/f_dis150aes.wav
ERL/data/es/f_dis201aes.wav
ERL/data/es/f_dis202aes.wav
ERL/data/es/f_dis204aes.wav
ERL/data/es/f_dis205aes.wav
ERL_Spanish-1.0.4.dist-info/METADATA
ERL_Spanish-1.0.4.dist-info/WHEEL
ERL_Spanish-1.0.4.dist-info/top_level.txt
ERL_Spanish-1.0.4.dist-info/RECORD
