Metadata-Version: 2.1
Name: ERL-Spanish
Version: 1.0.4
Summary: ERL: Emotion Recognition Library
Home-page: https://github.com/estefaaa02/ERL
Author: Mario Gómez, Estefanía Pérez, Victoria Núñez
Author-email: mgomezcam@unbosque.edu.co, eperezt@unbosque.edu.co, vnunezd@unbosque.edu.co
License: GPLv3 License
Platform: UNKNOWN
Requires-Dist: pyaudioanalysis (==0.3.7)
Requires-Dist: pydub
Requires-Dist: audiosegment (==0.23.0)
Requires-Dist: eyed3 (==0.9.6)
Requires-Dist: speechrecognition (==3.8.1)
Requires-Dist: google-cloud-speech (>=2.9.0)
Requires-Dist: nltk (==3.2.5)
Requires-Dist: pandas (==1.3.4)
Requires-Dist: numpy (==1.19.2)
Requires-Dist: keras (==2.6.0)
Requires-Dist: sklearn
Requires-Dist: matplotlib (==3.4.3)
Requires-Dist: tensorflow (==2.6.0)
Requires-Dist: tqdm
